README.txt
setup.cfg
setup.py
GraphLab_Service_Client.egg-info/PKG-INFO
GraphLab_Service_Client.egg-info/SOURCES.txt
GraphLab_Service_Client.egg-info/dependency_links.txt
GraphLab_Service_Client.egg-info/pbr.json
GraphLab_Service_Client.egg-info/requires.txt
GraphLab_Service_Client.egg-info/top_level.txt
graphlab_service_client/__init__.py
graphlab_service_client/_client.py
test/test.py